[{"__type__":"cc.SpriteFrame","content":{"name":"16_chat_content3","texture":"e3e7fac9-428e-4fb5-bdd2-dd0aa24c826f","rect":[0,28,345,28],"offset":[0,0],"originalSize":[345,28]}},{"__type__":"cc.SpriteFrame","content":{"name":"15_chat_content1","texture":"e3e7fac9-428e-4fb5-bdd2-dd0aa24c826f","rect":[0,56,369,28],"offset":[0,0],"originalSize":[369,28]}},{"__type__":"cc.SpriteFrame","content":{"name":"16_chat_content5","texture":"e3e7fac9-428e-4fb5-bdd2-dd0aa24c826f","rect":[345,28,361,28],"offset":[0,0],"originalSize":[361,28]}},{"__type__":"cc.SpriteFrame","content":{"name":"16_chat_content2","texture":"e3e7fac9-428e-4fb5-bdd2-dd0aa24c826f","rect":[331,0,320,28],"offset":[0,0],"originalSize":[320,28]}},{"__type__":"cc.SpriteFrame","content":{"name":"15_chat_content4","texture":"e3e7fac9-428e-4fb5-bdd2-dd0aa24c826f","rect":[329,84,352,28],"offset":[0,0],"originalSize":[352,28]}},{"__type__":"cc.SpriteFrame","content":{"name":"15_chat_content2","texture":"e3e7fac9-428e-4fb5-bdd2-dd0aa24c826f","rect":[0,84,329,28],"offset":[0,0],"originalSize":[329,28]}},{"__type__":"cc.SpriteFrame","content":{"name":"16_chat_content4","texture":"e3e7fac9-428e-4fb5-bdd2-dd0aa24c826f","rect":[651,0,320,28],"offset":[0,0],"originalSize":[320,28]}},{"__type__":"cc.SpriteFrame","content":{"name":"15_chat_content5","texture":"e3e7fac9-428e-4fb5-bdd2-dd0aa24c826f","rect":[681,84,260,28],"offset":[0,0],"originalSize":[260,28]}},{"__type__":"cc.SpriteFrame","content":{"name":"15_chat_content3","texture":"e3e7fac9-428e-4fb5-bdd2-dd0aa24c826f","rect":[369,56,329,28],"offset":[0,0],"originalSize":[329,28]}},{"__type__":"cc.SpriteAtlas","_name":"chat.plist","_spriteFrames":{"15_chat_content1":{"__uuid__":"0d3542de-28fd-47ce-a16e-f47d8b8dbc05"},"15_chat_content2":{"__uuid__":"473e563d-3cee-4b31-b94d-1d5c9b0c1066"},"15_chat_content3":{"__uuid__":"88ab30a6-42d1-41d3-a7bf-3e93c3d0eda3"},"15_chat_content4":{"__uuid__":"1a6b3b1a-5b4e-4f3b-8791-8086041d3470"},"15_chat_content5":{"__uuid__":"65f3c800-a818-4ca5-80a0-245e298acffb"},"15_chat_content_bg":{"__uuid__":"a1e8f45a-be2b-4b9b-9510-fccae3b08a1a"},"16_chat_content1":{"__uuid__":"f79c0de1-ac11-4ad8-8f3f-3c2530beb178"},"16_chat_content2":{"__uuid__":"16d8e45e-51eb-454b-82ff-5ecf6d081a7e"},"16_chat_content3":{"__uuid__":"002f3303-22fe-4a13-91bc-4e16ea67e781"},"16_chat_content4":{"__uuid__":"4a7462ac-8bee-4cf1-aeb5-0c221c511a15"},"16_chat_content5":{"__uuid__":"13324c83-127a-497d-a6bf-492b20e90e50"}}},{"__type__":"cc.SpriteFrame","content":{"name":"16_chat_content1","texture":"e3e7fac9-428e-4fb5-bdd2-dd0aa24c826f","rect":[0,0,331,28],"offset":[0,0],"originalSize":[331,28]}}]