[{"__type__":"cc.SpriteFrame","content":{"name":"4_times30","texture":"e10598da-84c6-4a31-b4be-0b00f7f4eecf","rect":[0,116,154,88],"offset":[0,0],"originalSize":[154,88]}},{"__type__":"cc.SpriteFrame","content":{"name":"4_right","texture":"e10598da-84c6-4a31-b4be-0b00f7f4eecf","rect":[0,0,42,42],"offset":[0,0],"originalSize":[42,42]}},{"__type__":"cc.SpriteFrame","content":{"name":"4_input_bg","texture":"e10598da-84c6-4a31-b4be-0b00f7f4eecf","rect":[0,64,146,52],"offset":[0,0],"originalSize":[146,52]}},{"__type__":"cc.SpriteFrame","content":{"name":"4_times10","texture":"e10598da-84c6-4a31-b4be-0b00f7f4eecf","rect":[0,292,154,88],"offset":[0,0],"originalSize":[154,88]}},{"__type__":"cc.SpriteFrame","content":{"name":"4_masonry","texture":"e10598da-84c6-4a31-b4be-0b00f7f4eecf","rect":[84,0,63,53],"offset":[0,0],"originalSize":[63,53]}},{"__type__":"cc.SpriteFrame","content":{"name":"4_kuang","texture":"e10598da-84c6-4a31-b4be-0b00f7f4eecf","rect":[42,0,42,42],"offset":[0,0],"originalSize":[42,42]}},{"__type__":"cc.SpriteFrame","content":{"name":"4_times20","texture":"e10598da-84c6-4a31-b4be-0b00f7f4eecf","rect":[0,204,154,88],"offset":[0,0],"originalSize":[154,88]}}]